LICENSE
MANIFEST.in
README.md
settings.ini
setup.cfg
dependencies/B_series_coefficients.npy
dependencies/Re_correction.npy
ship_model_lib/__init__.py
ship_model_lib/_modidx.py
ship_model_lib/added_resistance.py
ship_model_lib/calm_water_resistance.py
ship_model_lib/machinery.py
ship_model_lib/operation_profile_structure.py
ship_model_lib/propulsor.py
ship_model_lib/ship_dimensions.py
ship_model_lib/ship_model.py
ship_model_lib/types.py
ship_model_lib/utility.py
ship_model_lib/data/__init__.py
ship_model_lib/data/create_table.py
ship_model_lib/data/drag_coefficient.csv
ship_model_lib.egg-info/PKG-INFO
ship_model_lib.egg-info/SOURCES.txt
ship_model_lib.egg-info/dependency_links.txt
ship_model_lib.egg-info/entry_points.txt
ship_model_lib.egg-info/not-zip-safe
ship_model_lib.egg-info/requires.txt
ship_model_lib.egg-info/top_level.txt
tests/test_added_resistance.py
tests/test_machinery.py
tests/test_propulsor.py
tests/test_ship_model.py
ship_model_lib-1.0.2.dist-info/LICENSE
ship_model_lib-1.0.2.dist-info/METADATA
ship_model_lib-1.0.2.dist-info/WHEEL
ship_model_lib-1.0.2.dist-info/entry_points.txt
ship_model_lib-1.0.2.dist-info/top_level.txt
ship_model_lib-1.0.2.dist-info/RECORD
